<?xml version = '1.0' encoding = 'UTF-8'?>
<Relation class="oracle.dbtools.crest.model.design.logical.Relation" name="Relation_28" directorySegmentName="seg_0" id="B73EA99B-3244-C1A7-8FFB-153D1ED8C311">
<createdBy>Intel</createdBy>
<createdTime>2022-02-09 04:06:13 UTC</createdTime>
<ownerDesignName>G2_TF_E22A</ownerDesignName>
<importedID>B6D1C555-EEE9-2D98-F465-790CC6A5A0D8</importedID>
<engineerTo>
<item key="B46B0E09-DC3F-ACA6-B445-D83A2AC6A172" value="true"/>
<item key="B9B736CC-ED98-F109-8330-E394C7F372BB" value="true"/>
</engineerTo>
<sourcePk>938DD306-A188-6B23-3008-70EA6368FC61</sourcePk>
<identifying>true</identifying>
<optionalSource>false</optionalSource>
<optionalTarget>false</optionalTarget>
<sourceCardinality>1</sourceCardinality>
<sourceEntity>E9D7A02F-8DC2-53AA-B32F-7EC8B3EEE5E5</sourceEntity>
<targetCardinalityString>*</targetCardinalityString>
<targetEntity>E2399238-BE01-C47D-3A21-89D5D1CBA104</targetEntity>
<transferable>true</transferable>
<deleteRule>NO ACTION</deleteRule>
</Relation>